bankstatementextractor_final/BanksExtractor.py
bankstatementextractor_final/Incom_expense.py
bankstatementextractor_final/__init__.py
bankstatementextractor_final/banks.py
bankstatementextractor_final/banks_utils.py
bankstatementextractor_final/constants.py
bankstatementextractor_final/global_percentiles.json
bankstatementextractor_final/keywords.csv
bankstatementextractor_final/test.py
bankstatementextractor_final/throw_away.csv
bankstatementextractor_final/models/.DS_Store
bankstatementextractor_final/models/best.pt
bankstatementextractor_final/models/categories.csv
bankstatementextractor_final/models/lean/.DS_Store
bankstatementextractor_final/models/lean/labels
bankstatementextractor_final/models/lean/0.9384675110399379/.DS_Store
bankstatementextractor_final/models/lean/0.9384675110399379/keras_metadata.pb
bankstatementextractor_final/models/lean/0.9384675110399379/saved_model.pb
bankstatementextractor_final/models/lean/0.9384675110399379/variables/variables.data-00000-of-00001
bankstatementextractor_final/models/lean/0.9384675110399379/variables/variables.index
bankstatementextractor_final/models/places/.DS_Store
bankstatementextractor_final/models/places/categories.csv
bankstatementextractor_final/models/places/0.706/.DS_Store
bankstatementextractor_final/models/places/0.706/keras_metadata.pb
bankstatementextractor_final/models/places/0.706/saved_model.pb
bankstatementextractor_final/models/places/0.706/variables/variables.data-00000-of-00001
bankstatementextractor_final/models/places/0.706/variables/variables.index
bankstatementextractor_final/models/places/0.726/.DS_Store
bankstatementextractor_final/models/places/0.726/keras_metadata.pb
bankstatementextractor_final/models/places/0.726/saved_model.pb
bankstatementextractor_final/models/places/0.726/variables/variables.data-00000-of-00001
bankstatementextractor_final/models/places/0.726/variables/variables.index
bankstatementextractor_final/models/words/.DS_Store
bankstatementextractor_final-1.1.5.dist-info/LICENSE
bankstatementextractor_final-1.1.5.dist-info/METADATA
bankstatementextractor_final-1.1.5.dist-info/WHEEL
bankstatementextractor_final-1.1.5.dist-info/top_level.txt
bankstatementextractor_final-1.1.5.dist-info/RECORD
