Metadata-Version: 2.1
Name: bankstatementextractor-final
Version: 1.1.5
Summary: This repository contains a Python program designed to extract Optical Character Recognition (OCR) data from bank statements, detect income and classify expenses
Home-page: 
Author: Anjali
Author-email: anjalimenon217@gmail.com
Classifier: Programming Language :: Python :: 3
Classifier: License :: OSI Approved :: MIT License
Classifier: Operating System :: OS Independent
Requires-Python: >=3.7
License-File: LICENSE
Requires-Dist: setuptools
Requires-Dist: fitz
Requires-Dist: PyMuPDF (==1.23.3)
Requires-Dist: numpy
Requires-Dist: scipy
Requires-Dist: pandas
Requires-Dist: Unidecode
Requires-Dist: DateTime
Requires-Dist: Pillow
Requires-Dist: PyPDF2
Requires-Dist: Python-IO
Requires-Dist: pdf2image
Requires-Dist: torch
Requires-Dist: opencv-python
Requires-Dist: scikit-learn
Requires-Dist: transformers
